pip_search/__init__.py
pip_search/__main__.py
pip_search/pip_search.py
pip_search/utils.py
pip_search-0.0.14.dist-info/METADATA
pip_search-0.0.14.dist-info/WHEEL
pip_search-0.0.14.dist-info/entry_points.txt
pip_search-0.0.14.dist-info/top_level.txt
pip_search-0.0.14.dist-info/RECORD
