Metadata-Version: 2.4
Name: pip_search
Version: 0.0.14
Summary: A package to search like pip used to, via PyPi
Home-page: https://github.com/victorgarric/pip_search
Author: Victor Garric
Author-email: victor.garric@gmail.com
Classifier: Programming Language :: Python :: 3
Classifier: License :: OSI Approved :: MIT License
Classifier: Operating System :: OS Independent
Requires-Python: >=3.2
Requires-Dist: bs4
Requires-Dist: requests
Requires-Dist: rich
Dynamic: author
Dynamic: author-email
Dynamic: classifier
Dynamic: description
Dynamic: description-content-type
Dynamic: home-page
Dynamic: requires-dist
Dynamic: requires-python
Dynamic: summary
